rsm/server.py
rsm/__init__.py
rsm/static/index.html
rsm/static/fonts/glyphicons-halflings-regular.ttf
rsm/static/fonts/glyphicons-halflings-regular.woff
rsm/static/fonts/glyphicons-halflings-regular.woff2
rsm/static/fonts/glyphicons-halflings-regular.eot
rsm/static/fonts/glyphicons-halflings-regular.svg
rsm/static/img/helioslite-logo.png
rsm/static/img/favicon.ico
rsm/static/js/app.min-7fac2f60.js
rsm/static/css/app.min-703ec38b.css
reverse_ssh_manager-1.2.dist-info/DESCRIPTION.rst
reverse_ssh_manager-1.2.dist-info/entry_points.txt
reverse_ssh_manager-1.2.dist-info/WHEEL
reverse_ssh_manager-1.2.dist-info/top_level.txt
reverse_ssh_manager-1.2.dist-info/RECORD
reverse_ssh_manager-1.2.dist-info/METADATA
reverse_ssh_manager-1.2.dist-info/metadata.json
