Metadata-Version: 2.0
Name: reverse-ssh-manager
Version: 1.2
Summary: reverse-ssh-manager allows to manage reverse ssh connections through a web application
Home-page: https://github.com/bbinet/reverse-ssh-manager
Author: Bruno Binet
Author-email: bruno.binet@gmail.com
License: MIT
Keywords: ssh,tunnel,reverse,manage,web,application
Platform: UNKNOWN
Classifier: Development Status :: 4 - Beta
Classifier: Intended Audience :: Developers
Classifier: License :: OSI Approved :: MIT License
Classifier: Operating System :: MacOS :: MacOS X
Classifier: Operating System :: POSIX :: Linux
Classifier: Operating System :: Unix
Classifier: Programming Language :: Python
Classifier: Programming Language :: Python :: 2.6
Classifier: Programming Language :: Python :: 2.7
Requires-Dist: bottle
Requires-Dist: psutil
